moneykit/__init__.py
moneykit/api_client.py
moneykit/api_response.py
moneykit/configuration.py
moneykit/exceptions.py
moneykit/py.typed
moneykit/rest.py
moneykit/api/__init__.py
moneykit/api/access_token_api.py
moneykit/api/account_numbers_api.py
moneykit/api/accounts_api.py
moneykit/api/identity_api.py
moneykit/api/institutions_api.py
moneykit/api/investments_api.py
moneykit/api/link_session_api.py
moneykit/api/links_api.py
moneykit/api/products_api.py
moneykit/api/transactions_api.py
moneykit/api/users_api.py
moneykit/api/webhooks_api.py
moneykit/models/__init__.py
moneykit/models/account_balances.py
moneykit/models/account_group.py
moneykit/models/account_identity.py
moneykit/models/account_import_data.py
moneykit/models/account_numbers_legacy20230218.py
moneykit/models/account_response.py
moneykit/models/account_with_account_numbers_legacy20230218.py
moneykit/models/ach_number.py
moneykit/models/address.py
moneykit/models/api_error_auth_expired_access_token_response.py
moneykit/models/api_error_auth_unauthorized_response.py
moneykit/models/api_error_rate_limit_exceeded_response.py
moneykit/models/api_public_transactions_get_transactions_response.py
moneykit/models/api_public_transactions_legacy_get_transactions_response.py
moneykit/models/app_client_response.py
moneykit/models/app_link_state_changed_webhook.py
moneykit/models/app_response.py
moneykit/models/bacs_number.py
moneykit/models/basic_account_details.py
moneykit/models/body.py
moneykit/models/bud_category.py
moneykit/models/bud_primary_category.py
moneykit/models/bud_subcategory.py
moneykit/models/country.py
moneykit/models/create_access_token_response.py
moneykit/models/create_link_session_request.py
moneykit/models/create_link_session_response.py
moneykit/models/cursor_pagination.py
moneykit/models/custom_sandbox_account.py
moneykit/models/custom_sandbox_data.py
moneykit/models/customer_user.py
moneykit/models/customer_user_email.py
moneykit/models/customer_user_phone.py
moneykit/models/eft_number.py
moneykit-0.2.3.dist-info/METADATA
moneykit-0.2.3.dist-info/WHEEL
moneykit-0.2.3.dist-info/top_level.txt
moneykit-0.2.3.dist-info/RECORD
