Metadata-Version: 2.4
Name: moneykit
Version: 0.2.3
Summary: MoneyKit API
Keywords: OpenAPI,OpenAPI-Generator,MoneyKit API
Requires-Python: >=3.8
Requires-Dist: urllib3>=1.25.3
Requires-Dist: python-dateutil>=2.8.2
Requires-Dist: pydantic>=2
Requires-Dist: typing-extensions>=4.7.1
